alice_py_ycf/__init__.py
alice_py_ycf/main.py
alice_py_ycf/scene.py
alice_py_ycf-0.2.3.dist-info/METADATA
alice_py_ycf-0.2.3.dist-info/WHEEL
alice_py_ycf-0.2.3.dist-info/top_level.txt
alice_py_ycf-0.2.3.dist-info/RECORD
