Metadata-Version: 2.1
Name: alice-py-ycf
Version: 0.2.3
Summary: Module for easy writing of Yandex Alice skills.
Home-page: https://github.com/Aleksandr-Nevs/alice-py-ycf
Author: Aleks_Nevs
Author-email: WebAlek@yandex.ru
Keywords: Alice dialog,Python,Yandex
Classifier: Programming Language :: Python :: 3.8
Classifier: License :: OSI Approved :: MIT License
Classifier: Operating System :: OS Independent
Requires-Python: >=3.8
